scp_sdk/__init__.py
scp_sdk/core/__init__.py
scp_sdk/core/export.py
scp_sdk/core/graph.py
scp_sdk/core/manifest.py
scp_sdk/core/models.py
scp_sdk/integrations/__init__.py
scp_sdk/integrations/base.py
scp_sdk/integrations/config.py
scp_sdk/integrations/registry.py
scp_sdk/integrations/utils.py
scp_sdk/testing/__init__.py
scp_sdk/testing/cli.py
scp_sdk/testing/fixtures.py
scp_sdk/utils/__init__.py
scp_sdk/utils/tier.py
scp_sdk-0.2.2.dist-info/METADATA
scp_sdk-0.2.2.dist-info/WHEEL
scp_sdk-0.2.2.dist-info/licenses/LICENSE
scp_sdk-0.2.2.dist-info/RECORD
