Metadata-Version: 2.4
Name: scp-sdk
Version: 0.2.2
Summary: Python SDK for System Capability Protocol - programmatic manifest/graph access and integration framework
Project-URL: Homepage, https://systemcapabilityprotocol.com/
Project-URL: Documentation, https://systemcapabilityprotocol.com/sdk
Project-URL: Repository, https://github.com/krackenservices/scp-sdk.git
Project-URL: Issues, https://github.com/krackenservices/scp-sdk/issues
Author-email: Kracken Services <scp@krackenservices.com>
License: MIT
License-File: LICENSE
Keywords: architecture,dependency-graph,scp,service-mesh,system-capability-protocol
Classifier: Development Status :: 4 - Beta
Classifier: Intended Audience :: Developers
Classifier: License :: OSI Approved :: MIT License
Classifier: Operating System :: OS Independent
Classifier: Programming Language :: Python :: 3
Classifier: Programming Language :: Python :: 3.12
Classifier: Programming Language :: Python :: 3.13
Classifier: Topic :: Software Development :: Libraries :: Python Modules
Classifier: Typing :: Typed
Requires-Python: >=3.12
Requires-Dist: httpx>=0.25
Requires-Dist: opentelemetry-api>=1.20.0
Requires-Dist: pydantic-yaml>=1.3.0
Requires-Dist: pydantic>=2.0
Requires-Dist: pyyaml>=6.0
Requires-Dist: tenacity>=8.0.0
Provides-Extra: integrations
Requires-Dist: rich>=13.0; extra == 'integrations'
Provides-Extra: runtime
Requires-Dist: opentelemetry-instrumentation>=0.41b0; extra == 'runtime'
Requires-Dist: opentelemetry-sdk>=1.20.0; extra == 'runtime'
